funpipe/__init__.py
funpipe/bam.py
funpipe/fasta.py
funpipe/gatk.py
funpipe/microbiome.py
funpipe/phylo.py
funpipe/picard.py
funpipe/sv.py
funpipe/utils.py
funpipe/vcf.py
funpipe/vcftools.py
funpipe/scripts/bam_qc_metr.py
funpipe/scripts/coverage_analysis.py
funpipe/scripts/coverage_barplot.R
funpipe/scripts/dep_per_win.pl
funpipe/scripts/fastqc.py
funpipe/scripts/filter_gatk_genotypes.py
funpipe/scripts/genot_concord.py
funpipe/scripts/get_ref_path.py
funpipe/scripts/patch_ref_contigs.py
funpipe/scripts/pct_reads_per_species.py
funpipe/scripts/phylo_analysis.py
funpipe/scripts/pilon_metrics
funpipe/scripts/qc_metr_plot.R
funpipe/scripts/run_pilon.py
funpipe/scripts/run_ploidy.py
funpipe/scripts/run_snpeff.py
funpipe/scripts/snpeff_db.sh
funpipe/scripts/vcf_qc_metr.py
funpipe/scripts/vcf_snp_to_fasta.py
funpipe-0.1.0.data/scripts/bam_qc_metr.py
funpipe-0.1.0.data/scripts/coverage_analysis.py
funpipe-0.1.0.data/scripts/coverage_barplot.R
funpipe-0.1.0.data/scripts/dep_per_win.pl
funpipe-0.1.0.data/scripts/fastqc.py
funpipe-0.1.0.data/scripts/filter_gatk_genotypes.py
funpipe-0.1.0.data/scripts/genot_concord.py
funpipe-0.1.0.data/scripts/get_ref_path.py
funpipe-0.1.0.data/scripts/patch_ref_contigs.py
funpipe-0.1.0.data/scripts/pct_reads_per_species.py
funpipe-0.1.0.data/scripts/phylo_analysis.py
funpipe-0.1.0.data/scripts/pilon_metrics
funpipe-0.1.0.data/scripts/qc_metr_plot.R
funpipe-0.1.0.data/scripts/run_pilon.py
funpipe-0.1.0.data/scripts/run_ploidy.py
funpipe-0.1.0.data/scripts/run_snpeff.py
funpipe-0.1.0.data/scripts/snpeff_db.sh
funpipe-0.1.0.data/scripts/vcf_qc_metr.py
funpipe-0.1.0.data/scripts/vcf_snp_to_fasta.py
funpipe-0.1.0.dist-info/LICENSE
funpipe-0.1.0.dist-info/METADATA
funpipe-0.1.0.dist-info/WHEEL
funpipe-0.1.0.dist-info/top_level.txt
funpipe-0.1.0.dist-info/RECORD
