Metadata-Version: 2.1
Name: funpipe
Version: 0.1.0
Summary: A pipeline for analyzing fungal genomic data
Home-page: https://github.com/broadinstitute/funpipe
Author: Xiao Li
Author-email: xiaoli@broadinstitute.org
License: MIT
Project-URL: Bug tracker, https://github.com/broadinstitute/funpipe/issues
Project-URL: Documentation, https://github.com/broadinstitute/funpipe/README.md
Keywords: bioinformatics
Platform: UNKNOWN
Classifier: Intended Audience :: Science/Research
Classifier: Development Status :: 3 - Alpha
Classifier: License :: OSI Approved :: MIT License
Classifier: Programming Language :: Python :: 3.4
Classifier: Topic :: Scientific/Engineering :: Bio-Informatics
Classifier: Natural Language :: English
Requires-Dist: argparse (>=1.1)
Requires-Dist: crimson (>=0.4.0)
Requires-Dist: pandas (>=0.23.4)
Requires-Dist: matplotlib (>=3.0.2)
Requires-Dist: seaborn (>=0.9.0)
